evaldet/__init__.py
evaldet/detections.py
evaldet/dist.py
evaldet/py.typed
evaldet/tracks.py
evaldet/det/__init__.py
evaldet/det/coco.py
evaldet/det/utils.py
evaldet/mot/__init__.py
evaldet/mot/alta.py
evaldet/mot/clearmot.py
evaldet/mot/hota.py
evaldet/mot/identity.py
evaldet/mot/motmetrics.py
evaldet/mot/utils.py
evaldet/utils/__init__.py
evaldet/utils/prec_recall.py
evaldet/utils/timer.py
evaldet-0.4.2.dist-info/METADATA
evaldet-0.4.2.dist-info/WHEEL
evaldet-0.4.2.dist-info/licenses/LICENSE
evaldet-0.4.2.dist-info/RECORD
